[1,["c7byte0ghArIapeWAVk5zW@6c48a"],["_textureSource"],["cc.SpriteFrame"],0,[{"name":"baby1","rect":{"x":0,"y":0,"width":559,"height":955},"offset":{"x":0,"y":0},"originalSize":{"width":559,"height":955},"rotated":false,"capInsets":[0,0,0,0],"vertices":{"rawPosition":[-279.5,-477.5,0,279.5,-477.5,0,-279.5,477.5,0,279.5,477.5,0],"indexes":[0,1,2,2,1,3],"uv":[0,955,559,955,0,0,559,0],"nuv":[0,0,1,0,0,1,1,1],"minPos":{"x":-279.5,"y":-477.5,"z":0},"maxPos":{"x":279.5,"y":477.5,"z":0}},"packable":true,"pixelsToUnit":100,"pivot":{"x":0.5,"y":0.5},"meshType":0}],[0],0,[0],[0],[0]]
